irc_api/__init__.py
irc_api/bot.py
irc_api/commands.py
irc_api/history.py
irc_api/irc.py
irc_api/message.py
irc_api-1.0.7.dist-info/LICENSE
irc_api-1.0.7.dist-info/METADATA
irc_api-1.0.7.dist-info/WHEEL
irc_api-1.0.7.dist-info/top_level.txt
irc_api-1.0.7.dist-info/RECORD
